pnt2/.DS_Store
pnt2/__init__.py
pnt2/src/.DS_Store
pnt2/src/calc_similarity.py
pnt2/src/canonical.py
pnt2/src/cfg_pnt2.py
pnt2/src/create_table.py
pnt2/src/draw_canonical.py
pnt2/src/draw_image_warp.py
pnt2/src/draw_magn.py
pnt2/src/draw_peaks.py
pnt2/src/draw_result.py
pnt2/src/draw_similarity_map.py
pnt2/src/draw_utils.py
pnt2/src/get_angle.py
pnt2/src/get_peaks.py
pnt2/src/get_similarity.py
pnt2/src/magnitude.py
pnt2/src/utils.py
pnt2/src/utils_list.py
pnt2-1.0.3.dist-info/METADATA
pnt2-1.0.3.dist-info/WHEEL
pnt2-1.0.3.dist-info/RECORD
