Metadata-Version: 2.1
Name: pnt2
Version: 1.0.3
Summary: "pnt2" - calculating the degree of similarity between geometric figures of different shapes (by 2 points)
License: MIT
Author: Boris Kravtsov
Author-email: kravtsov.development@gmail.com
Requires-Python: >=3.11,<4.0
Classifier: License :: OSI Approved :: MIT License
Classifier: Programming Language :: Python :: 3
Classifier: Programming Language :: Python :: 3.11
Requires-Dist: opencv-python-headless (>=4.8.1.78,<5.0.0.0)
